{
    "types": [
        "projects",
        "certifications",
        "experiences"
    ],
    "entries": [
        {
            "id": "aws-fundamentals-course",
            "name": "Cloud Fundamentals: AWS Services for C# Developers",
            "brief": "An introduction to the basic AWS services presented by Nick Chapsas",
            "tags": [
                "AWS",
                "C#",
                "S3",
                "Lambda",
                "DynamoDB",
                "SQS",
                "SNS",
                "Secrets Manager"
            ],
            "type": "certifications",
            "access": null,
            "source": null
        },
        {
            "id": "greenpyrus-ltd",
            "position": "Junior Software Developer (Part-Time)",
            "name": "GreenPyrus Ltd.",
            "brief": "Creating intuitive interfaces for desktop applications and data management.",
            "summary": [
                "Developed a suite of bespoke utility software to automate menial tasks to improve productivity. Created an intuitive UI with PyQt5 to make use of the library.",
                "Designed a database to hold the company’s inventory data and currency exchange rates (as a cache), making up time for senior employees due to the API’s timeout used APIs request limit.",
                "Implemented a REST API using ASP.NET Core to interact with the data through a standard interface. Also created a corresponding frontend with React and Typescript to visualise the data in a simple, tabular form and make edits to inventory data simple.",
                "Basic TDD with xUnit and mocking with Moq for unit testing.",
                "Created an AWS Lambda to automatically update the database when there was a change to inventory Excel files in an Amazon S3 bucket, to create an alternative interface to access inventory data."
            ],
            "tags": [
                "Python",
                "MariaDb",
                "PyQt5",
                "Lambda",
                "ReactJS",
                "S3",
                "ASP.NET Core",
                "Redis",
                "ECR",
                "IAM",
                "CI/CD",
                "Postman",
                "Docker",
                "AWS",
                "TDD"
            ],
            "type": "experiences",
            "started": "Mar 2021",
            "ended": "Sep 2023"
        },
        {
            "id": "portfolio",
            "name": "Personal Portfolio",
            "brief": "My personal portfolio website which I use to showcase my projects and experiences.",
            "tags": [
                "React",
                "Typescript",
                "Javascript",
                "HTML",
                "CSS",
                "AWS",
                "EC2",
                "ECR",
                "Docker",
                "Frontend"
            ],
            "type": "projects",
            "access": "https://portfolio.davidrosental.co.uk",
            "source": "https://github.com/LittleAksMax/portfolio.git"
        },
        {
            "id": "rest-api-course",
            "name": "From Zero to Hero: REST APIs in .NET",
            "brief": "Deep dive into creating robust and fully-equipped REST APIs presented by Nick Chapsas",
            "tags": [
                "C#",
                "REST",
                "PostgreSQL",
                "ASP.NET Core",
                "Authentication",
                "JWT",
                "API KEY",
                "Postman",
                "Docker"
            ],
            "type": "certifications",
            "access": null,
            "source": "https://github.com/LittleAksMax/aspnet-rest-template.git"
        },
        {
            "id": "docker-course",
            "name": "From Zero to Hero: Docker for Developers",
            "brief": "An introduction to effectively utilising Docker and fundamental Docker concepts presented by Dan Clarke",
            "tags": [
                "Docker"
            ],
            "type": "certifications",
            "access": null,
            "source": null
        }
    ]
}